ril-0.4.0.dist-info/METADATA
ril-0.4.0.dist-info/WHEEL
ril-0.4.0.dist-info/license_files/LICENSE
ril/__init__.py
ril/__init__.pyi
ril/py.typed
ril/ril.pyd
ril-0.4.0.dist-info/RECORD
