Metadata-Version: 2.1
Name: ril
Version: 0.4.0
Requires-Dist: sphinx; extra == 'docs'
Requires-Dist: furo; extra == 'docs'
Requires-Dist: sphinxext-opengraph; extra == 'docs'
Requires-Dist: sphinx-copybutton; extra == 'docs'
Provides-Extra: docs
License-File: LICENSE
Summary: Rust Imaging Library's Python binding: A performant and high-level image processing library for Python written in Rust
Keywords: ril,imaging,image,processing,editing
Home-Page: https://github.com/Cryptex-github/ril-py
Author: Cryptex
License: MIT
Requires-Python: >=3.7
Project-URL: homepage, https://github.com/Cryptex-github/ril-py
